setuptools_scm/.git_archival.txt
setuptools_scm/__init__.py
setuptools_scm/__main__.py
setuptools_scm/_cli.py
setuptools_scm/_compat.py
setuptools_scm/_config.py
setuptools_scm/_entrypoints.py
setuptools_scm/_get_version_impl.py
setuptools_scm/_log.py
setuptools_scm/_modify_version.py
setuptools_scm/_node_utils.py
setuptools_scm/_overrides.py
setuptools_scm/_requirement_cls.py
setuptools_scm/_run_cmd.py
setuptools_scm/_types.py
setuptools_scm/_version_cls.py
setuptools_scm/discover.py
setuptools_scm/fallbacks.py
setuptools_scm/git.py
setuptools_scm/hg.py
setuptools_scm/hg_git.py
setuptools_scm/integration.py
setuptools_scm/py.typed
setuptools_scm/scm_workdir.py
setuptools_scm/version.py
setuptools_scm/_file_finders/__init__.py
setuptools_scm/_file_finders/git.py
setuptools_scm/_file_finders/hg.py
setuptools_scm/_file_finders/pathtools.py
setuptools_scm/_integration/__init__.py
setuptools_scm/_integration/dump_version.py
setuptools_scm/_integration/pyproject_reading.py
setuptools_scm/_integration/setup_cfg.py
setuptools_scm/_integration/setuptools.py
setuptools_scm/_integration/toml.py
setuptools_scm/_integration/version_inference.py
setuptools_scm-9.1.1.dist-info/licenses/LICENSE
setuptools_scm-9.1.1.dist-info/METADATA
setuptools_scm-9.1.1.dist-info/WHEEL
setuptools_scm-9.1.1.dist-info/entry_points.txt
setuptools_scm-9.1.1.dist-info/top_level.txt
setuptools_scm-9.1.1.dist-info/RECORD
