Metadata-Version: 2.4
Name: setuptools-scm
Version: 9.1.1
Summary: the blessed package to manage your versions by scm tags
Author-email: Ronny Pfannschmidt <opensource@ronnypfannschmidt.de>
License: Permission is hereby granted, free of charge, to any person obtaining a copy
Project-URL: documentation, https://setuptools-scm.readthedocs.io/
Project-URL: repository, https://github.com/pypa/setuptools-scm/
Classifier: Development Status :: 5 - Production/Stable
Classifier: Intended Audience :: Developers
Classifier: License :: OSI Approved :: MIT License
Classifier: Programming Language :: Python
Classifier: Programming Language :: Python :: 3 :: Only
Classifier: Programming Language :: Python :: 3.8
Classifier: Programming Language :: Python :: 3.9
Classifier: Programming Language :: Python :: 3.10
Classifier: Programming Language :: Python :: 3.11
Classifier: Programming Language :: Python :: 3.12
Classifier: Programming Language :: Python :: 3.13
Classifier: Topic :: Software Development :: Libraries
Classifier: Topic :: Software Development :: Version Control
Classifier: Topic :: System :: Software Distribution
Classifier: Topic :: Utilities
Requires-Python: >=3.8
License-File: LICENSE
Requires-Dist: packaging>=20
Requires-Dist: setuptools
Requires-Dist: tomli>=1; python_version < "3.11"
Requires-Dist: typing-extensions; python_version < "3.10"
Provides-Extra: rich
Requires-Dist: rich; extra == "rich"
Provides-Extra: toml
Dynamic: license-file
